src/__init__.py
src/__main__.py
src/assets/README.md
src/assets/config/eula.txt
src/assets/config/recommended-args.txt
src/assets/docker/minecraft.Dockerfile
src/assets/docker/minecraft.dockerignore
src/assets/docker/node.Dockerfile
src/assets/docker/node.dockerignore
src/assets/docker/python.Dockerfile
src/assets/docker/python.dockerignore
src/assets/scripts/run.sh
src/assets/templates/.env.j2
src/assets/templates/docker-compose.yml.j2
src/assets/templates/template.json
src/cli/__init__.py
src/cli/builder.py
src/cli/custom_group.py
src/cli/manager.py
src/cli/menu.py
src/cli/param_types.py
src/core/__init__.py
src/core/docker.py
src/core/downloader.py
src/core/files.py
src/utils/__init__.py
src/utils/cli.py
minecraftdockercli-0.11.0.dist-info/METADATA
minecraftdockercli-0.11.0.dist-info/WHEEL
minecraftdockercli-0.11.0.dist-info/entry_points.txt
minecraftdockercli-0.11.0.dist-info/licenses/LICENSE
minecraftdockercli-0.11.0.dist-info/RECORD
