Metadata-Version: 2.4
Name: MinecraftDockerCLI
Version: 0.11.0
Summary: CLI tool to enhance and simplify containerization of Minecraft servers
License: MIT
License-File: LICENSE
Keywords: minecraft,docker,server
Author: Dtar380
Maintainer: Dtar380
Requires-Python: >=3.13,<4.0
Classifier: Development Status :: 3 - Alpha
Classifier: Environment :: Console
Classifier: Intended Audience :: Developers
Classifier: Intended Audience :: Other Audience
Classifier: Intended Audience :: System Administrators
Classifier: License :: OSI Approved :: MIT License
Classifier: Programming Language :: Python :: 3
Classifier: Programming Language :: Python :: 3.13
Classifier: Programming Language :: Python :: 3.14
Classifier: Topic :: Games/Entertainment
Classifier: Topic :: System :: Installation/Setup
Requires-Dist: click (>=8.3.0,<9.0.0)
Requires-Dist: importlib-resources (>=6.5.2,<7.0.0)
Requires-Dist: inquirerpy (>=0.3.4,<0.4.0)
Requires-Dist: jinja2 (>=3.1.6,<4.0.0)
Requires-Dist: psutil (>=7.1.3,<8.0.0)
Requires-Dist: requests (>=2.32.5,<3.0.0)
Requires-Dist: yaspin (>=3.3.0,<4.0.0)
Project-URL: Bug Tracker, https://github.com/Dtar380/Minecraft-Dockerfile-CLI/issues
Project-URL: Documentation, https://minecraftdockercli.readthedocs.io/en/latest/
Project-URL: Homepage, https://github.com/dtar380/Minecraft-Dockerfile-CLI
Project-URL: Repository, https://github.com/dtar380/Minecraft-Dockerfile-CLI
